.gitignore
.travis.yml
CHANGES.txt
MANIFEST.in
README.rst
bootstrap.py
buildout.cfg
setup.py
isotoma/__init__.py
isotoma.recipe.zeopack.egg-info/PKG-INFO
isotoma.recipe.zeopack.egg-info/SOURCES.txt
isotoma.recipe.zeopack.egg-info/dependency_links.txt
isotoma.recipe.zeopack.egg-info/entry_points.txt
isotoma.recipe.zeopack.egg-info/namespace_packages.txt
isotoma.recipe.zeopack.egg-info/not-zip-safe
isotoma.recipe.zeopack.egg-info/requires.txt
isotoma.recipe.zeopack.egg-info/top_level.txt
isotoma/recipe/__init__.py
isotoma/recipe/zeopack/__init__.py
isotoma/recipe/zeopack/recipe.py
isotoma/recipe/zeopack/zeopack.py