Metadata-Version: 1.1
Name: isotoma.recipe.zeopack
Version: 0.0.1
Summary: Buildout recipes for zeopack.
Home-page: http://pypi.python.org/pypi/isotoma.recipe.zeopack
Author: John Carr
Author-email: john.carr@isotoma.com
License: Apache Software License
Keywords: buildout zeopack
Platform: UNKNOWN
Classifier: Framework :: Buildout
Classifier: Framework :: Buildout :: Recipe
Classifier: Intended Audience :: System Administrators
Classifier: Operating System :: POSIX
Classifier: License :: OSI Approved :: Apache Software License
